pf_py_file/__init__.py
pf_py_file/pfpf_archive.py
pf_py_file/pfpf_file_reader.py
pf_py_file/pfpf_file_util.py
pf_py_file/pfpf_image_util.py
pf_py_file/pfpf_text_file_man.py
PF_PY_File-1.0.1.dist-info/LICENSE
PF_PY_File-1.0.1.dist-info/METADATA
PF_PY_File-1.0.1.dist-info/WHEEL
PF_PY_File-1.0.1.dist-info/top_level.txt
PF_PY_File-1.0.1.dist-info/RECORD
