Metadata-Version: 2.1
Name: PF-PY-File
Version: 1.0.1
Summary: Python File Manager by Problem Fighter Library
Home-page: https://github.com/problemfighter/pf-py-file
Author: Problem Fighter
Author-email: problemfighter.com@gmail.com
License: Apache 2.0
Platform: any
Classifier: Intended Audience :: Developers
Classifier: License :: OSI Approved :: Apache Software License
Classifier: Programming Language :: Python
Requires-Dist: Pillow
Requires-Dist: PF-PY-Common
